[{"name": "npbench.azimint_naive.numba_mlir.Benchmark.time_benchmark", "idx": 0, "pretty_name": "npbench.azimint_naive.numba_mlir.Benchmark.time_benchmark('S')", "last_rev": 1392, "last_value": 0.13207047060132027, "last_err": 0.0, "prev_value": null, "change_rev": null}, {"name": "npbench.azimint_naive.numba_mlir.Benchmark.time_benchmark", "idx": 1, "pretty_name": "npbench.azimint_naive.numba_mlir.Benchmark.time_benchmark('M')", "last_rev": 1392, "last_value": 1.4164949357509613, "last_err": 0.0, "prev_value": null, "change_rev": null}, {"name": "npbench.azimint_naive.numba_mlir.Benchmark.time_benchmark", "idx": 2, "pretty_name": "npbench.azimint_naive.numba_mlir.Benchmark.time_benchmark('paper')", "last_rev": 1392, "last_value": 0.3494841456413269, "last_err": 0.0, "prev_value": null, "change_rev": null}]